AmbuView/AmbuView_README.ipynb
AmbuView/Devon_2021_Census_Population_by_town.csv
AmbuView/Full_Graph_Generation.py
AmbuView/LICENSE.txt
AmbuView/Torbay_test_data_population_density.csv
AmbuView/__init__.py
AmbuView/data_processing.py
AmbuView/distance_calculations.py
AmbuView/environment.yml
AmbuView/isochrone_map.py
AmbuView/map_visualization.py
AmbuView/nomis_2023_12_31_000343.csv
AmbuView/optimization.py
AmbuView/requirements.txt
AmbuView/test_Full_Graph_Generation.ipynb
AmbuView/test_data_processing.ipynb
AmbuView/test_data_torquay_locations.csv
AmbuView/test_distance_calculations.ipynb
AmbuView/test_map_visualisation.ipynb
AmbuView/test_optimization.ipynb
AmbuView-0.1.3.dist-info/LICENSE.txt
AmbuView-0.1.3.dist-info/METADATA
AmbuView-0.1.3.dist-info/WHEEL
AmbuView-0.1.3.dist-info/top_level.txt
AmbuView-0.1.3.dist-info/RECORD
